setup.py
ledsign/__init__.py
ledsign/metadata.py
ledsign/am03127/__init__.py
ledsign/am03127/communication.py
ledsign/am03127/messages.py
ledsign/am03127/parsers.py
pyLEDSign.egg-info/PKG-INFO
pyLEDSign.egg-info/SOURCES.txt
pyLEDSign.egg-info/dependency_links.txt
pyLEDSign.egg-info/requires.txt
pyLEDSign.egg-info/top_level.txt