Metadata-Version: 1.0
Name: pyLEDSign
Version: 2.0.1
Summary: A LED message board library for Python
Home-page: https://github.com/Mezgrman/pyLEDSign
Author: Julian Metzler
Author-email: contact@mezgrman.de
License: AGPLv3
Keywords: led sign message board effect library wrapper serial scrolling text
Platform: UNKNOWN
